{
  "commentaires": [
    {
      "id": 1,
      "recette_id": 4,
      "nom": "Stefou",
      "texte": "DÉ-LI-CIEUX !  Surtout avec la version Angine de poitrine :)",
      "cree": "2026-07-14 16:20",
      "modifie": "2026-07-14 16:20",
      "reponses": [
        {
          "id": 2,
          "nom": "Mélo",
          "texte": "Merci 😊",
          "cree": "2026-07-14 20:29",
          "modifie": "2026-07-14 20:30"
        }
      ]
    },
    {
      "id": 3,
      "recette_id": 11,
      "nom": "Stefou",
      "texte": "Avec les dernières modif, ça sera 5 étoiles",
      "cree": "2026-07-15 00:59",
      "modifie": "2026-07-15 00:59",
      "reponses": []
    }
  ],
  "prochain_id": 4
}